README.md
setup.py
chromatin/__init__.py
chromatin/cli.py
chromatin/env.py
chromatin/host.py
chromatin/logging.py
chromatin/plugin.py
chromatin/venv.py
chromatin/venvs.py
chromatin.egg-info/PKG-INFO
chromatin.egg-info/SOURCES.txt
chromatin.egg-info/dependency_links.txt
chromatin.egg-info/entry_points.txt
chromatin.egg-info/requires.txt
chromatin.egg-info/top_level.txt
chromatin/plugins/__init__.py
chromatin/plugins/core/__init__.py
chromatin/plugins/core/main.py
chromatin/plugins/core/messages.py
chromatin/util/__init__.py
chromatin/util/resources.py