Metadata-Version: 1.0
Name: chromatin
Version: 0.12.0
Summary: neovim python plugin manager
Home-page: https://github.com/tek/chromatin
Author: Torsten Schmits
Author-email: torstenschmits@gmail.com
License: MIT
Platform: UNKNOWN
